odoo10_addon_product_contract-10.0.1.1.0-py2.7-nspkg.pth
odoo/addons/product_contract/README.rst
odoo/addons/product_contract/__init__.py
odoo/addons/product_contract/__manifest__.py
odoo/addons/product_contract/i18n/de.po
odoo/addons/product_contract/i18n/es.po
odoo/addons/product_contract/i18n/fi.po
odoo/addons/product_contract/i18n/fr.po
odoo/addons/product_contract/i18n/hi_IN.po
odoo/addons/product_contract/i18n/hr.po
odoo/addons/product_contract/i18n/hr_HR.po
odoo/addons/product_contract/i18n/it.po
odoo/addons/product_contract/i18n/nl.po
odoo/addons/product_contract/i18n/nl_NL.po
odoo/addons/product_contract/i18n/product_contract.pot
odoo/addons/product_contract/i18n/pt.po
odoo/addons/product_contract/i18n/pt_BR.po
odoo/addons/product_contract/i18n/ru.po
odoo/addons/product_contract/i18n/tr.po
odoo/addons/product_contract/i18n/tr_TR.po
odoo/addons/product_contract/models/__init__.py
odoo/addons/product_contract/models/product_template.py
odoo/addons/product_contract/models/sale_order.py
odoo/addons/product_contract/models/sale_order_line.py
odoo/addons/product_contract/static/description/icon.png
odoo/addons/product_contract/tests/__init__.py
odoo/addons/product_contract/tests/test_product_template.py
odoo/addons/product_contract/tests/test_sale_order.py
odoo/addons/product_contract/views/product_template_view.xml
odoo10_addon_product_contract-10.0.1.1.0.dist-info/METADATA
odoo10_addon_product_contract-10.0.1.1.0.dist-info/RECORD
odoo10_addon_product_contract-10.0.1.1.0.dist-info/WHEEL
odoo10_addon_product_contract-10.0.1.1.0.dist-info/namespace_packages.txt
odoo10_addon_product_contract-10.0.1.1.0.dist-info/top_level.txt
